tencentcloud_dlc_provider/__init__.py
tencentcloud_dlc_provider/hooks/__init__.py
tencentcloud_dlc_provider/hooks/dlc_hook.py
tencentcloud_dlc_provider/operators/__init__.py
tencentcloud_dlc_provider/operators/dlc_operator.py
tencentcloud_dlc_provider-0.0.3.dist-info/METADATA
tencentcloud_dlc_provider-0.0.3.dist-info/WHEEL
tencentcloud_dlc_provider-0.0.3.dist-info/entry_points.txt
tencentcloud_dlc_provider-0.0.3.dist-info/top_level.txt
tencentcloud_dlc_provider-0.0.3.dist-info/RECORD
